pyxqueue.py
pyxqueue-0.1.1.dist-info/LICENSE
pyxqueue-0.1.1.dist-info/METADATA
pyxqueue-0.1.1.dist-info/WHEEL
pyxqueue-0.1.1.dist-info/top_level.txt
pyxqueue-0.1.1.dist-info/RECORD
