Metadata-Version: 2.1
Name: pyxqueue
Version: 0.1.1
Summary: a multi-processes task queue using redis streams.
Home-page: https://github.com/FuGangqiang/pyxqueue
Author: FuGangqiang
Author-email: fu_gangqiang@qq.com
License: UNKNOWN
Project-URL: Bug Tracker, https://github.com/FuGangqiang/pyxqueue/issues
Project-URL: 中文文档, https://github.com/FuGangqiang/pyxqueue/blob/master/README-zh.md
Keywords: redis,stream,queue
Platform: UNKNOWN
Classifier: Programming Language :: Python :: 3
Classifier: Programming Language :: Python :: 3.7
Classifier: Environment :: Web Environment
Classifier: License :: OSI Approved :: MIT License
Classifier: Operating System :: OS Independent
Requires-Python: >=3.7
License-File: LICENSE
Requires-Dist: redis (>="3.0.0")
